ifmt/__init__.py
ifmt/py.typed
ifmt-0.0.0.dist-info/LICENSE
ifmt-0.0.0.dist-info/METADATA
ifmt-0.0.0.dist-info/WHEEL
ifmt-0.0.0.dist-info/top_level.txt
ifmt-0.0.0.dist-info/RECORD
